pymitt/__init__.py
pymitt/pymitt.py
pymitt-1.0.0.dist-info/LICENSE
pymitt-1.0.0.dist-info/METADATA
pymitt-1.0.0.dist-info/WHEEL
pymitt-1.0.0.dist-info/top_level.txt
pymitt-1.0.0.dist-info/RECORD
