Metadata-Version: 2.1
Name: pymitt
Version: 1.0.0
Summary: Minimal Python wrapper for Keymitt webhooks
Home-page: https://github.com/fedus/pymitt
Author: Federico Gentile
Author-email: gentfede+github@gmail.com
License: MIT
Platform: UNKNOWN
Classifier: License :: OSI Approved :: MIT License
Classifier: Programming Language :: Python :: 3
License-File: LICENSE
Requires-Dist: asyncio
Requires-Dist: aiohttp[speedups]
